archivetags/__init__.py
archivetags/tags.py
archivetags-0.1.0.dist-info/METADATA
archivetags-0.1.0.dist-info/WHEEL
archivetags-0.1.0.dist-info/top_level.txt
archivetags-0.1.0.dist-info/RECORD
