Metadata-Version: 2.1
Name: archivetags
Version: 0.1.0
Summary: archive dataset tags
Home-page: 
Author: Lily
Author-email: 
License: MIT
